[
  {
    "ContainingType": "CvAnalysisSystemProject.Controller.UserController",
    "Method": "Register",
    "RelativePath": "api/User",
    "HttpMethod": "POST",
    "IsController": true,
    "Order": 0,
    "Parameters": [
      {
        "Name": "request",
        "Type": "CvAnalysisSystem.Application.CQRS.Users.Handlers.Commands.Register\u002BCommand",
        "IsRequired": true
      }
    ],
    "ReturnTypes": []
  },
  {
    "ContainingType": "CvAnalysisSystemProject.Controller.UserController",
    "Method": "Login",
    "RelativePath": "api/User/Login",
    "HttpMethod": "POST",
    "IsController": true,
    "Order": 0,
    "Parameters": [
      {
        "Name": "request",
        "Type": "CvAnalysisSystem.Application.CQRS.Users.Handlers.Commands.Login\u002BLoginRequest",
        "IsRequired": true
      }
    ],
    "ReturnTypes": []
  }
]